vec_cache/__init__.py
vec_cache/core.py
vec_cache/data_models.py
vec_cache/utils.py
vec_cache-0.1.4.dist-info/METADATA
vec_cache-0.1.4.dist-info/WHEEL
vec_cache-0.1.4.dist-info/RECORD
